sepstring/main.py
sepstring-0.1.1.dist-info/METADATA
sepstring-0.1.1.dist-info/WHEEL
sepstring-0.1.1.dist-info/entry_points.txt
sepstring-0.1.1.dist-info/RECORD
