Metadata-Version: 2.1
Name: sepstring
Version: 0.1.1
Summary: Simple CLI to split strings
Author: Evan Voyles
Author-email: ejovo13@yahoo.com
Requires-Python: >=3.11,<4.0
Classifier: Programming Language :: Python :: 3
Classifier: Programming Language :: Python :: 3.11
Classifier: Programming Language :: Python :: 3.12
Requires-Dist: typer (>=0.15.0,<0.16.0)
